snmp_miner/__init__.py
snmp_miner/py.typed
snmp_miner-0.2.0.dist-info/WHEEL
snmp_miner-0.2.0.dist-info/METADATA
snmp_miner-0.2.0.dist-info/RECORD
