Metadata-Version: 2.4
Name: snmp-miner
Version: 0.2.0
Summary: Mines SNMP data from network devices in a nicely formatted way.
Author: Caio Salgado
Author-email: Caio Salgado <caio.csalgado@gmail.com>
License-Expression: MIT
Requires-Dist: pydantic~=2.12
Requires-Dist: pysnmp~=7.1
Requires-Python: >=3.13
